fastapi_aws/__init__.py
fastapi_aws/__main__.py
fastapi_aws/_version.py
fastapi_aws/authorizers.py
fastapi_aws/models.py
fastapi_aws/route.py
fastapi_aws/router.py
fastapi_aws/test_vtl_serializable_model.py
fastapi_aws/vtl_analyzer.py
fastapi_aws/vtl_serializable_model.py
fastapi_aws/integrations/__init__.py
fastapi_aws/integrations/dynamodb.py
fastapi_aws/integrations/lambda_fn.py
fastapi_aws/integrations/mock.py
fastapi_aws/integrations/s3.py
fastapi_aws/integrations/sns.py
fastapi_aws/integrations/step_function.py
fastapi_aws-0.0.11.dist-info/METADATA
fastapi_aws-0.0.11.dist-info/WHEEL
fastapi_aws-0.0.11.dist-info/top_level.txt
fastapi_aws-0.0.11.dist-info/RECORD
