Metadata-Version: 2.4
Name: fastapi-aws
Version: 0.0.11
Summary: AWS Integrations for FastAPI exported OpenAPI specifications
Home-page: https://github.com/bayinfosys/fastapi-aws
Author: Edward Grundy
Author-email: ed@bayis.co.uk
Classifier: Programming Language :: Python :: 3
Classifier: License :: OSI Approved :: MIT License
Classifier: Operating System :: OS Independent
Requires-Python: >=3.6
Requires-Dist: fastapi
Requires-Dist: httpx
Requires-Dist: uvicorn[standard]
Dynamic: author
Dynamic: author-email
Dynamic: classifier
Dynamic: description
Dynamic: description-content-type
Dynamic: home-page
Dynamic: requires-dist
Dynamic: requires-python
Dynamic: summary
